{
  "_class": "group",
  "do_objectID": "A00575CB-5A0B-4CD3-949D-7CEDF0CB17D6",
  "exportOptions": {
    "_class": "exportOptions",
    "exportFormats": [
    ],
    "includedLayerIds": [
    ],
    "layerOptions": 0,
    "shouldTrim": false
  },
  "frame": {
    "_class": "rect",
    "constrainProportions": false,
    "height": 83,
    "width": 112,
    "x": 248,
    "y": 13
  },
  "hasClickThrough": false,
  "isFlippedHorizontal": false,
  "isFlippedVertical": false,
  "isLocked": false,
  "isVisible": true,
  "layerListExpandedType": 0,
  "layers": [
    {
      "class": "shapeGroup",
      "id": "EE40F9E0-43A8-40D0-9B74-34A22C75AEC9"
    },
    {
      "class": "bitmap",
      "id": "2BB0F7C5-496D-41D1-A2DF-BE6E2F6B85DD"
    }
  ],
  "name": "Bitmap",
  "nameIsFixed": false,
  "resizingConstraint": 63,
  "resizingType": 0,
  "rotation": 0,
  "shouldBreakMaskChain": false,
  "style": {
    "_class": "style",
    "endDecorationType": 0,
    "miterLimit": 10,
    "startDecorationType": 0
  }
}