{
  "_class": "shapeGroup",
  "booleanOperation": 0,
  "clippingMaskMode": 0,
  "do_objectID": "284CA654-92F1-4443-8D4D-BF30777DD23E",
  "exportOptions": {
    "_class": "exportOptions",
    "exportFormats": [
    ],
    "includedLayerIds": [
    ],
    "layerOptions": 0,
    "shouldTrim": false
  },
  "frame": {
    "_class": "rect",
    "constrainProportions": false,
    "height": 25.94852017449665,
    "width": 23.2379752863996,
    "x": 0.008506666535943406,
    "y": 0.02661242505592723
  },
  "hasClickThrough": false,
  "hasClippingMask": false,
  "isFixedToViewport": false,
  "isFlippedHorizontal": false,
  "isFlippedVertical": false,
  "isLocked": false,
  "isVisible": true,
  "layerListExpandedType": 0,
  "layers": [
    {
      "class": "shapePath",
      "id": "9BFE73EF-06A8-41EB-B8E8-BD100111CF16"
    },
    {
      "class": "shapePath",
      "id": "7E06793C-07E9-4DE3-BDF7-B578E6D971EB"
    },
    {
      "class": "shapePath",
      "id": "320B0683-773A-4F34-BC93-EF3D6ECBF8DE"
    },
    {
      "class": "shapePath",
      "id": "BB6471E9-2F5F-4A94-A035-82F4D0CAABE2"
    },
    {
      "class": "shapePath",
      "id": "D29738E0-737E-4DA3-87B0-B3ACAD4C033F"
    }
  ],
  "name": "Shape",
  "nameIsFixed": false,
  "resizingConstraint": 63,
  "resizingType": 0,
  "rotation": 0,
  "shouldBreakMaskChain": false,
  "style": {
    "_class": "style",
    "endMarkerType": 0,
    "fills": [
      {
        "_class": "fill",
        "color": {
          "_class": "color",
          "alpha": 1,
          "blue": 0,
          "green": 0,
          "red": 0
        },
        "fillType": 0,
        "isEnabled": true,
        "noiseIndex": 0,
        "noiseIntensity": 0,
        "patternFillType": 1,
        "patternTileScale": 1
      }
    ],
    "miterLimit": 10,
    "startMarkerType": 0,
    "windingRule": 0
  },
  "windingRule": 0
}