{
  "_class": "oval",
  "booleanOperation": -1,
  "clippingMaskMode": 0,
  "do_objectID": "9F6B870D-2583-4C0B-AF7A-0A2C4EE9F1B1",
  "edited": true,
  "exportOptions": {
    "_class": "exportOptions",
    "do_objectID": "F772CDBD-9ECD-42D3-ABF5-8085ACF40C34",
    "exportFormats": [
    ],
    "includedLayerIds": [
    ],
    "layerOptions": 0,
    "shouldTrim": false
  },
  "frame": {
    "_class": "rect",
    "constrainProportions": false,
    "do_objectID": "2CE15D31-5ABB-4748-ABF8-C31A5776C0F0",
    "height": 5.086372267393729,
    "width": 5.101875818379761,
    "x": 130.3141468290719,
    "y": 21.61708213642333
  },
  "hasClippingMask": false,
  "isClosed": true,
  "isFixedToViewport": false,
  "isFlippedHorizontal": false,
  "isFlippedVertical": false,
  "isLocked": false,
  "isVisible": true,
  "layerListExpandedType": 0,
  "name": "Camera Boarder",
  "nameIsFixed": true,
  "pointRadiusBehaviour": 0,
  "points": [
    {
      "_class": "curvePoint",
      "cornerRadius": 0,
      "curveFrom": "{0.77614238858222961, 1.0000000000000007}",
      "curveMode": 2,
      "curveTo": "{0.22385761141777039, 1.0000000000000007}",
      "hasCurveFrom": true,
      "hasCurveTo": true,
      "point": "{0.5, 1.0000000000000007}"
    },
    {
      "_class": "curvePoint",
      "cornerRadius": 0,
      "curveFrom": "{1, 0.22385761141777052}",
      "curveMode": 2,
      "curveTo": "{1, 0.77614238858223017}",
      "hasCurveFrom": true,
      "hasCurveTo": true,
      "point": "{1, 0.50000000000000033}"
    },
    {
      "_class": "curvePoint",
      "cornerRadius": 0,
      "curveFrom": "{0.22385761141777039, 0}",
      "curveMode": 2,
      "curveTo": "{0.77614238858222961, 0}",
      "hasCurveFrom": true,
      "hasCurveTo": true,
      "point": "{0.5, 0}"
    },
    {
      "_class": "curvePoint",
      "cornerRadius": 0,
      "curveFrom": "{0, 0.77614238858223017}",
      "curveMode": 2,
      "curveTo": "{0, 0.22385761141777052}",
      "hasCurveFrom": true,
      "hasCurveTo": true,
      "point": "{0, 0.50000000000000033}"
    }
  ],
  "resizingConstraint": 63,
  "resizingType": 0,
  "rotation": 0,
  "shouldBreakMaskChain": false,
  "style": {
    "_class": "style",
    "blur": {
      "_class": "blur",
      "center": "{0.5, 0.5}",
      "do_objectID": "29F31891-8C52-4726-9B59-A2C6BD3661AE",
      "isEnabled": false,
      "motionAngle": 0,
      "radius": 15,
      "saturation": 1,
      "type": 0
    },
    "borders": [
      {
        "_class": "border",
        "color": {
          "_class": "color",
          "alpha": 1,
          "blue": 0.592,
          "green": 0.592,
          "red": 0.592
        },
        "fillType": 0,
        "isEnabled": false,
        "position": 0,
        "thickness": 1.5
      }
    ],
    "do_objectID": "41EB8D0E-EC04-4B5B-9C91-20E5DA024F7E",
    "endMarkerType": 0,
    "fills": [
      {
        "_class": "fill",
        "color": {
          "_class": "color",
          "alpha": 1,
          "blue": 0.05490196078431372,
          "green": 0.05490196078431372,
          "red": 0.05490196078431372
        },
        "fillType": 0,
        "gradient": {
          "_class": "gradient",
          "elipseLength": 0,
          "from": "{0.5, 0}",
          "gradientType": 0,
          "stops": [
            {
              "_class": "gradientStop",
              "color": {
                "_class": "color",
                "alpha": 1,
                "blue": 0.04594494047619048,
                "green": 0.04594494047619048,
                "red": 0.04594494047619048
              },
              "position": 0
            },
            {
              "_class": "gradientStop",
              "color": {
                "_class": "color",
                "alpha": 1,
                "blue": 0.1513206845238095,
                "green": 0.1513206845238095,
                "red": 0.1513206845238095
              },
              "position": 1
            }
          ],
          "to": "{0.5, 1}"
        },
        "isEnabled": true,
        "noiseIndex": 0,
        "noiseIntensity": 0,
        "patternFillType": 0,
        "patternTileScale": 1
      }
    ],
    "miterLimit": 10,
    "startMarkerType": 0,
    "windingRule": 1
  }
}