{
  "_class": "shapeGroup",
  "clippingMaskMode": 0,
  "do_objectID": "9C0D18E4-6773-498A-B93C-C7A4795C9580",
  "exportOptions": {
    "_class": "exportOptions",
    "exportFormats": [
    ],
    "includedLayerIds": [
    ],
    "layerOptions": 0,
    "shouldTrim": false
  },
  "frame": {
    "_class": "rect",
    "constrainProportions": false,
    "height": 1.287925696594428,
    "width": 7.520661157024794,
    "x": 9.239669421487633,
    "y": 24.69597523219818
  },
  "hasClickThrough": false,
  "hasClippingMask": false,
  "isFlippedHorizontal": false,
  "isFlippedVertical": false,
  "isLocked": false,
  "isVisible": true,
  "layerListExpandedType": 0,
  "layers": [
    {
      "class": "shapePath",
      "id": "35795F3D-A06A-4F0C-9F70-35C3BEACAE0D"
    },
    {
      "class": "shapePath",
      "id": "1D518B76-0C2D-4F0C-89AF-5B48C811E5A5"
    }
  ],
  "name": "Shape",
  "nameIsFixed": false,
  "resizingConstraint": 63,
  "resizingType": 0,
  "rotation": 0,
  "shouldBreakMaskChain": false,
  "style": {
    "sharedObjectID": "05CEC80D-6679-410C-929C-24A5DE55F42E"
  },
  "windingRule": 0
}