{
  "_class": "text",
  "attributedString": {
    "_class": "attributedString",
    "attributes": [
      {
        "_class": "stringAttribute",
        "attributes": {
          "MSAttributedStringColorAttribute": {
            "_class": "color",
            "alpha": 1,
            "blue": 0.1066960171,
            "green": 0.007513228338,
            "red": 0.816203773
          },
          "MSAttributedStringFontAttribute": {
            "_class": "fontDescriptor",
            "attributes": {
              "name": "FZZJ-ZZGKTFW",
              "size": 116
            }
          },
          "paragraphStyle": {
            "_class": "paragraphStyle",
            "alignment": 2
          }
        },
        "length": 1,
        "location": 0
      }
    ],
    "string": "旅"
  },
  "automaticallyDrawOnUnderlyingPath": false,
  "booleanOperation": 0,
  "clippingMaskMode": 0,
  "do_objectID": "7A1949FA-568A-4FA0-9707-1F269F23F53A",
  "dontSynchroniseWithSymbol": false,
  "exportOptions": {
    "_class": "exportOptions",
    "do_objectID": "65A2AE31-ACCB-449A-8E15-C9488A0D07FE",
    "exportFormats": [
    ],
    "includedLayerIds": [
    ],
    "layerOptions": 0,
    "shouldTrim": false
  },
  "frame": {
    "_class": "rect",
    "constrainProportions": false,
    "do_objectID": "089B5A30-3BFF-46D3-B50E-EEB31D7DBF05",
    "height": 126,
    "width": 116,
    "x": 253,
    "y": 0
  },
  "glyphBounds": "{{6, 13}, {104, 94}}",
  "hasClippingMask": false,
  "isFixedToViewport": false,
  "isFlippedHorizontal": false,
  "isFlippedVertical": false,
  "isLocked": false,
  "isVisible": true,
  "layerListExpandedType": 0,
  "lineSpacingBehaviour": 2,
  "name": "旅",
  "nameIsFixed": false,
  "resizingConstraint": 47,
  "resizingType": 0,
  "rotation": 0,
  "shouldBreakMaskChain": false,
  "style": {
    "_class": "style",
    "do_objectID": "88D8EA16-653D-4E12-8253-37953ECE872D",
    "endMarkerType": 0,
    "miterLimit": 10,
    "startMarkerType": 0,
    "textStyle": {
      "_class": "textStyle",
      "do_objectID": "6A5DF6E1-5840-4066-9D8A-C22AF05F2826",
      "encodedAttributes": {
        "MSAttributedStringColorAttribute": {
          "_class": "color",
          "alpha": 1,
          "blue": 0.1066960171,
          "green": 0.007513228338,
          "red": 0.816203773
        },
        "MSAttributedStringFontAttribute": {
          "_class": "fontDescriptor",
          "attributes": {
            "name": "FZZJ-ZZGKTFW",
            "size": 116
          }
        },
        "paragraphStyle": {
          "_class": "paragraphStyle",
          "alignment": 2
        }
      },
      "verticalAlignment": 0
    },
    "windingRule": 1
  },
  "textBehaviour": 0,
  "userInfo": {
    "com.sketchplugins.wechat.selectionDom1": {
      "selection1": "80E72995-A760-4040-9A20-EB2DCA352BF5"
    },
    "com.sketchplugins.wechat.selectionDom2": {
      "selection2": "80E72995-A760-4040-9A20-EB2DCA352BF5"
    }
  }
}